[
  {
    "timestamp": 1690166513,
    "hrAnomalies": [
      80,
      78,
      78
    ],
    "rrAnomalies": [
      710,
      715,
      715
    ]
  },
  {
    "timestamp": 1690167562,
    "hrAnomalies": [
      83
    ],
    "rrAnomalies": [
      443
    ]
  },
  {
    "timestamp": 1690168162,
    "hrAnomalies": [
      78,
      79,
      80,
      80,
      81,
      81,
      76,
      78,
      79,
      80,
      82,
      83,
      77,
      78,
      79,
      79,
      83,
      83,
      80,
      76,
      77,
      78,
      79,
      81,
      81,
      81,
      82,
      84,
      84,
      84,
      84
    ],
    "rrAnomalies": [
      730,
      706,
      732,
      737,
      734,
      726,
      701,
      737,
      738,
      718,
      691,
      719,
      709,
      723,
      739,
      712,
      704,
      726,
      728,
      712,
      716,
      733,
      719,
      729,
      733,
      727,
      700,
      720,
      740,
      714,
      734
    ]
  },
  {
    "timestamp": 1690168763,
    "hrAnomalies": [
      71,
      72,
      74,
      75,
      76
    ],
    "rrAnomalies": [
      813,
      791,
      730,
      736,
      778
    ]
  },
  {
    "timestamp": 1690171207,
    "hrAnomalies": [
      82,
      85,
      82,
      87,
      85,
      86,
      83,
      83,
      83,
      87
    ],
    "rrAnomalies": [
      690,
      650,
      660,
      704,
      699,
      672,
      692,
      704,
      668,
      684
    ]
  },
  {
    "timestamp": 1690171807,
    "hrAnomalies": [
      78,
      81,
      84,
      86,
      82,
      85,
      80,
      86,
      93,
      98,
      100,
      100,
      98,
      93,
      92,
      92,
      91,
      89,
      89,
      88,
      88,
      88,
      88
    ],
    "rrAnomalies": [
      685,
      674,
      669,
      681,
      671,
      684,
      677,
      638,
      620,
      618,
      613,
      621,
      635,
      670,
      675,
      681,
      714,
      714,
      714,
      700,
      709,
      712,
      725
    ]
  }
]