[
  {
    "timestamp": 1684708171,
    "hrAnomalies": [
      80,
      79,
      78,
      78,
      77,
      67,
      68,
      69,
      70,
      69,
      70,
      71,
      72
    ],
    "rrAnomalies": [
      863,
      861,
      874,
      882,
      885,
      798,
      786,
      781,
      808,
      808,
      796,
      800,
      822
    ]
  },
  {
    "timestamp": 1684708771,
    "hrAnomalies": [
      71,
      72,
      72,
      72,
      74,
      75,
      77,
      79,
      80,
      80,
      80,
      78,
      70
    ],
    "rrAnomalies": [
      812,
      808,
      787,
      778,
      756,
      749,
      726,
      736,
      757,
      794,
      824,
      879,
      808
    ]
  },
  {
    "timestamp": 1684710037,
    "hrAnomalies": [
      72,
      73,
      74,
      75,
      75,
      75,
      75,
      75,
      76,
      76,
      77,
      77,
      78,
      78,
      79,
      79,
      79,
      78,
      70,
      72,
      73,
      69,
      71,
      72,
      75,
      75,
      77,
      79,
      79,
      79,
      79
    ],
    "rrAnomalies": [
      805,
      801,
      801,
      802,
      808,
      804,
      808,
      807,
      780,
      777,
      772,
      767,
      762,
      757,
      782,
      794,
      802,
      803,
      795,
      796,
      797,
      809,
      761,
      761,
      747,
      746,
      743,
      764,
      768,
      775,
      830
    ]
  },
  {
    "timestamp": 1684710637,
    "hrAnomalies": [
      73,
      70,
      70,
      72,
      74,
      79,
      80,
      81,
      81,
      81,
      80,
      79,
      64,
      68,
      72,
      65,
      67,
      68,
      71,
      74,
      75,
      78,
      78,
      79,
      79,
      80,
      80,
      80,
      80,
      81,
      82,
      83,
      84,
      84,
      83,
      83,
      82,
      79,
      72,
      73,
      75,
      76,
      76,
      72,
      75,
      78,
      79,
      82,
      83,
      83,
      83,
      83,
      82,
      81,
      80,
      79,
      79
    ],
    "rrAnomalies": [
      302,
      439,
      360,
      739,
      724,
      730,
      730,
      743,
      762,
      857,
      866,
      954,
      682,
      786,
      790,
      790,
      800,
      776,
      742,
      730,
      735,
      742,
      756,
      761,
      781,
      774,
      778,
      758,
      746,
      724,
      713,
      714,
      726,
      764,
      788,
      816,
      847,
      912,
      762,
      750,
      771,
      787,
      797,
      746,
      706,
      694,
      699,
      718,
      725,
      723,
      759,
      775,
      842,
      856,
      844,
      847,
      856
    ]
  },
  {
    "timestamp": 1684711237,
    "hrAnomalies": [
      74,
      76,
      77,
      77,
      77,
      75,
      75,
      75,
      76,
      77,
      78,
      80,
      82,
      84,
      85,
      85,
      85,
      84,
      82,
      70,
      70,
      73,
      76,
      77,
      78,
      75,
      76,
      77,
      78,
      79,
      79,
      73,
      73,
      75,
      76,
      77,
      79,
      79,
      80,
      80,
      80,
      70,
      70,
      69
    ],
    "rrAnomalies": [
      766,
      770,
      771,
      782,
      790,
      784,
      789,
      791,
      761,
      769,
      572,
      710,
      697,
      696,
      731,
      771,
      830,
      872,
      871,
      776,
      756,
      742,
      738,
      745,
      783,
      756,
      753,
      737,
      745,
      764,
      785,
      788,
      781,
      768,
      746,
      731,
      730,
      739,
      761,
      779,
      802,
      685,
      782,
      580
    ]
  },
  {
    "timestamp": 1684711838,
    "hrAnomalies": [
      70,
      71,
      74,
      75,
      76,
      76,
      77,
      71,
      73,
      73,
      74,
      74,
      76,
      76,
      76,
      75,
      76,
      78,
      78,
      79,
      79,
      79,
      78,
      73,
      77,
      80,
      81,
      81,
      83,
      86,
      87,
      87,
      89,
      89,
      87,
      87,
      86,
      83,
      82,
      81,
      80,
      80,
      80,
      73,
      73,
      75,
      78,
      83,
      89,
      92,
      92,
      91,
      86,
      81,
      80,
      73,
      74,
      76,
      79,
      79,
      80,
      80,
      80
    ],
    "rrAnomalies": [
      759,
      753,
      777,
      786,
      766,
      762,
      787,
      801,
      795,
      802,
      771,
      769,
      801,
      792,
      804,
      751,
      743,
      745,
      755,
      769,
      782,
      804,
      802,
      739,
      736,
      724,
      705,
      698,
      694,
      553,
      7256,
      660,
      692,
      725,
      750,
      790,
      798,
      804,
      785,
      802,
      800,
      828,
      865,
      495,
      768,
      710,
      663,
      638,
      635,
      680,
      748,
      871,
      894,
      885,
      861,
      768,
      738,
      723,
      729,
      737,
      760,
      765,
      766
    ]
  },
  {
    "timestamp": 1684712439,
    "hrAnomalies": [
      81,
      83,
      85,
      86,
      84,
      85,
      87,
      88,
      88,
      73,
      77,
      79,
      80,
      83,
      83,
      84,
      84,
      84,
      84,
      85,
      88,
      89,
      92,
      92,
      89,
      89,
      86,
      83,
      83,
      83,
      81,
      83,
      84,
      85,
      85,
      85,
      85,
      85,
      85,
      85,
      85,
      85,
      86,
      89,
      90,
      97,
      101,
      101,
      103,
      103,
      110,
      114,
      115,
      116,
      116,
      119,
      119,
      119,
      119,
      119,
      119,
      119,
      119,
      119,
      118,
      117,
      115,
      115,
      115,
      114,
      114,
      114,
      114,
      113,
      112,
      109,
      109,
      109,
      109,
      109,
      109,
      109,
      108,
      107,
      107,
      106,
      105,
      104,
      104,
      104,
      104,
      104,
      104,
      104,
      111,
      116,
      117,
      117,
      118,
      118,
      119,
      119,
      119,
      114,
      113,
      119,
      119,
      117,
      117,
      117,
      117,
      112,
      111,
      111,
      110,
      110,
      110,
      110,
      109,
      117,
      118,
      118,
      118,
      119,
      119,
      119,
      119,
      119,
      119,
      119,
      119,
      119,
      117,
      117,
      117,
      117,
      117,
      119,
      120,
      120,
      120,
      120,
      120,
      120,
      120,
      118,
      117,
      113,
      113,
      112,
      112,
      110,
      109,
      108,
      108,
      108,
      106,
      106,
      106,
      106
    ],
    "rrAnomalies": [
      712,
      672,
      691,
      709,
      711,
      683,
      669,
      680,
      697,
      718,
      697,
      334,
      515,
      284,
      371,
      367,
      311,
      513,
      517,
      511,
      517,
      522,
      286,
      615,
      315,
      570,
      660,
      453,
      304,
      457,
      512,
      672,
      696,
      653,
      597,
      379,
      474,
      467,
      565,
      607,
      521,
      389,
      521,
      285,
      307,
      614,
      510,
      520,
      514,
      516,
      392,
      525,
      514,
      515,
      1040,
      417,
      617,
      285,
      610,
      515,
      514,
      1043,
      516,
      260,
      1517,
      513,
      512,
      410,
      1038,
      824,
      427,
      517,
      515,
      858,
      386,
      393,
      618,
      1039,
      2062,
      946,
      815,
      305,
      313,
      719,
      796,
      758,
      502,
      369,
      660,
      332,
      322,
      760,
      511,
      525,
      856,
      367,
      1554,
      1093,
      4593,
      2273,
      270,
      759,
      1512,
      1555,
      515,
      524,
      514,
      349,
      757,
      451,
      307,
      654,
      311,
      613,
      415,
      1756,
      799,
      1025,
      1467,
      821,
      1227,
      842,
      513,
      509,
      346,
      1553,
      746,
      518,
      512,
      324,
      326,
      715,
      656,
      516,
      910,
      512,
      512,
      516,
      516,
      302,
      738,
      455,
      419,
      349,
      1199,
      779,
      980,
      753,
      517,
      1028,
      874,
      888,
      1125,
      578,
      513,
      956,
      422,
      615,
      516,
      591
    ]
  },
  {
    "timestamp": 1684713039,
    "hrAnomalies": [
      113,
      116,
      114,
      114,
      113,
      116,
      117,
      117,
      117,
      116,
      112,
      110,
      110,
      110,
      110,
      110,
      119,
      119,
      119,
      119,
      119,
      118,
      118,
      117,
      118,
      118
    ],
    "rrAnomalies": [
      571,
      676,
      368,
      511,
      524,
      633,
      330,
      294,
      387,
      308,
      639,
      284,
      514,
      513,
      513,
      355,
      522,
      472,
      327,
      516,
      517,
      557,
      635,
      509,
      372,
      514
    ]
  }
]